{
  "Name": "D-Latch",
  "NameLocation": 0,
  "ChipType": 0,
  "Size": {
    "x": 1.175,
    "y": 0.5
  },
  "Colour": {
    "r": 0.4379869,
    "g": 0.675835431,
    "b": 0.943197,
    "a": 1
  },
  "InputPins":[
    {
      "Name":"DATA",
      "ID":1693085897,
      "Position":{
        "x":-6.5,
        "y":2.0625
      },
      "BitCount":1,
      "Colour":0,
      "ValueDisplayMode":0
    },
    {
      "Name":"STORE",
      "ID":54145089,
      "Position":{
        "x":-6.5,
        "y":0.3125
      },
      "BitCount":1,
      "Colour":0,
      "ValueDisplayMode":0
    }
  ],
  "OutputPins":[
    {
      "Name":"OUT",
      "ID":1387481346,
      "Position":{
        "x":2.25,
        "y":1.8125
      },
      "BitCount":1,
      "Colour":0,
      "ValueDisplayMode":0
    }
  ],
  "SubChips":[
    {
      "Name":"NOT",
      "ID":1046347392,
      "Label":"",
      "Position":{
        "x":-3.9525,
        "y":0.0625
      },
      "OutputPinColourInfo":[{"PinColour":0,"PinID":1913880116}],
      "InternalData":null
    },
    {
      "Name":"NAND",
      "ID":657092695,
      "Label":"",
      "Position":{
        "x":-2.875,
        "y":1.9375
      },
      "OutputPinColourInfo":[{"PinColour":0,"PinID":2}],
      "InternalData":null
    },
    {
      "Name":"NAND",
      "ID":2147267646,
      "Label":"",
      "Position":{
        "x":-2.875,
        "y":0.1875
      },
      "OutputPinColourInfo":[{"PinColour":0,"PinID":2}],
      "InternalData":null
    },
    {
      "Name":"NAND",
      "ID":903688702,
      "Label":"",
      "Position":{
        "x":-1.0,
        "y":1.8125
      },
      "OutputPinColourInfo":[{"PinColour":0,"PinID":2}],
      "InternalData":null
    },
    {
      "Name":"NAND",
      "ID":2008160765,
      "Label":"",
      "Position":{
        "x":-1.0,
        "y":0.3125
      },
      "OutputPinColourInfo":[{"PinColour":0,"PinID":2}],
      "InternalData":null
    }
  ],
  "Wires":[
    {
      "SourcePinAddress":{
        "PinID":0,
        "PinOwnerID":1693085897
      },
      "TargetPinAddress":{
        "PinID":373910735,
        "PinOwnerID":1046347392
      },
      "ConnectionType":0,
      "ConnectedWireIndex":-1,
      "ConnectedWireSegmentIndex":-1,
      "Points":[{"x":0.0,"y":0.0},{"x":-4.62513,"y":2.07449},{"x":-4.625,"y":0.0625},{"x":0.0,"y":0.0}]
    },
    {
      "SourcePinAddress":{
        "PinID":2,
        "PinOwnerID":657092695
      },
      "TargetPinAddress":{
        "PinID":0,
        "PinOwnerID":903688702
      },
      "ConnectionType":0,
      "ConnectedWireIndex":-1,
      "ConnectedWireSegmentIndex":-1,
      "Points":[{"x":0.0,"y":0.0},{"x":0.0,"y":0.0}]
    },
    {
      "SourcePinAddress":{
        "PinID":2,
        "PinOwnerID":2147267646
      },
      "TargetPinAddress":{
        "PinID":1,
        "PinOwnerID":2008160765
      },
      "ConnectionType":0,
      "ConnectedWireIndex":-1,
      "ConnectedWireSegmentIndex":-1,
      "Points":[{"x":0.0,"y":0.0},{"x":0.0,"y":0.0}]
    },
    {
      "SourcePinAddress":{
        "PinID":1913880116,
        "PinOwnerID":1046347392
      },
      "TargetPinAddress":{
        "PinID":1,
        "PinOwnerID":2147267646
      },
      "ConnectionType":0,
      "ConnectedWireIndex":-1,
      "ConnectedWireSegmentIndex":-1,
      "Points":[{"x":0.0,"y":0.0},{"x":0.0,"y":0.0}]
    },
    {
      "SourcePinAddress":{
        "PinID":0,
        "PinOwnerID":54145089
      },
      "TargetPinAddress":{
        "PinID":0,
        "PinOwnerID":2147267646
      },
      "ConnectionType":0,
      "ConnectedWireIndex":-1,
      "ConnectedWireSegmentIndex":-1,
      "Points":[{"x":0.0,"y":0.0},{"x":0.0,"y":0.0}]
    },
    {
      "SourcePinAddress":{
        "PinID":0,
        "PinOwnerID":1693085897
      },
      "TargetPinAddress":{
        "PinID":0,
        "PinOwnerID":657092695
      },
      "ConnectionType":1,
      "ConnectedWireIndex":0,
      "ConnectedWireSegmentIndex":1,
      "Points":[{"x":-4.62513,"y":2.0625},{"x":0.0,"y":0.0}]
    },
    {
      "SourcePinAddress":{
        "PinID":0,
        "PinOwnerID":54145089
      },
      "TargetPinAddress":{
        "PinID":1,
        "PinOwnerID":657092695
      },
      "ConnectionType":1,
      "ConnectedWireIndex":4,
      "ConnectedWireSegmentIndex":0,
      "Points":[{"x":-4.9375,"y":0.3125},{"x":-4.9375,"y":1.8125},{"x":0.0,"y":0.0}]
    },
    {
      "SourcePinAddress":{
        "PinID":2,
        "PinOwnerID":903688702
      },
      "TargetPinAddress":{
        "PinID":0,
        "PinOwnerID":2008160765
      },
      "ConnectionType":0,
      "ConnectedWireIndex":-1,
      "ConnectedWireSegmentIndex":-1,
      "Points":[{"x":0.0,"y":0.0},{"x":-0.0625,"y":1.8125},{"x":-0.0625,"y":1.3125},{"x":-1.9375,"y":1.3125},{"x":-1.9375,"y":0.4375},{"x":0.0,"y":0.0}]
    },
    {
      "SourcePinAddress":{
        "PinID":2,
        "PinOwnerID":2008160765
      },
      "TargetPinAddress":{
        "PinID":1,
        "PinOwnerID":903688702
      },
      "ConnectionType":0,
      "ConnectedWireIndex":-1,
      "ConnectedWireSegmentIndex":-1,
      "Points":[{"x":0.0,"y":0.0},{"x":-0.0625,"y":0.3125},{"x":-0.0625,"y":0.8125},{"x":-1.8125,"y":0.8125},{"x":-1.8125,"y":1.6875},{"x":0.0,"y":0.0}]
    },
    {
      "SourcePinAddress":{
        "PinID":2,
        "PinOwnerID":903688702
      },
      "TargetPinAddress":{
        "PinID":0,
        "PinOwnerID":1387481346
      },
      "ConnectionType":1,
      "ConnectedWireIndex":7,
      "ConnectedWireSegmentIndex":0,
      "Points":[{"x":-0.0625,"y":1.8125},{"x":0.0,"y":0.0}]
    }
  ],
  "Displays": null
}